Metadata-Version: 2.1
Name: TCObservability
Version: 1.0.6
Summary: A lib to easily add observality to Google cloud functions
Author: Maycon Guimaraes
Author-email: maycon.guimaraes@tc.com.br
License: UNKNOWN
Platform: UNKNOWN
License-File: LICENSE.txt
